consolePys/PyConsole.py
consolePys/__init__.py
consolePys-0.1.0.dist-info/LICENCE.txt
consolePys-0.1.0.dist-info/METADATA
consolePys-0.1.0.dist-info/WHEEL
consolePys-0.1.0.dist-info/top_level.txt
consolePys-0.1.0.dist-info/RECORD
